<annotation>
	<folder>edit_data_rang</folder>
	<filename>PN0024.jpg</filename>
	<path>D:\python\object-detection-PyTorch\dataset\edit_data_rang\PN0024.jpg</path>
	<source>
		<database>Unknown</database>
	</source>
	<size>
		<width>2473</width>
		<height>1252</height>
		<depth>1</depth>
	</size>
	<segmented>0</segmented>
	<object>
		<name>4</name>
		<pose>Unspecified</pose>
		<truncated>0</truncated>
		<difficult>0</difficult>
		<bndbox>
			<xmin>1741</xmin>
			<ymin>886</ymin>
			<xmax>1804</xmax>
			<ymax>951</ymax>
		</bndbox>
	</object>
</annotation>
